odoo/addons/crm_sale_order_line_contract_rest_api/README.rst
odoo/addons/crm_sale_order_line_contract_rest_api/__init__.py
odoo/addons/crm_sale_order_line_contract_rest_api/__manifest__.py
odoo/addons/crm_sale_order_line_contract_rest_api/services/__init__.py
odoo/addons/crm_sale_order_line_contract_rest_api/services/crm_lead_services.py
odoo/addons/crm_sale_order_line_contract_rest_api/services/schemas.py
odoo12_addon_crm_sale_order_line_contract_rest_api-12.0.0.0.3.dist-info/METADATA
odoo12_addon_crm_sale_order_line_contract_rest_api-12.0.0.0.3.dist-info/WHEEL
odoo12_addon_crm_sale_order_line_contract_rest_api-12.0.0.0.3.dist-info/top_level.txt
odoo12_addon_crm_sale_order_line_contract_rest_api-12.0.0.0.3.dist-info/RECORD
