Metadata-Version: 2.1
Name: odoo12-addon-crm-sale-order-line-contract-rest-api
Version: 12.0.0.0.3
Summary: Enhance CRM order lines Rest API to add contract specific configs
Home-page: 
Author: Coopdevs Treball SCCL
Classifier: Programming Language :: Python
Classifier: Framework :: Odoo
Classifier: Framework :: Odoo :: 12.0
Requires-Python: >=3.5
Requires-Dist: odoo12-addon-crm-sale-order-line-rest-api
Requires-Dist: odoo (<12.1dev,>=12.0a)
